assert_files/__init__.py
assert_files/assert_files.py
assert_files/file.py
assert_files-0.1.3.dist-info/LICENSE.txt
assert_files-0.1.3.dist-info/METADATA
assert_files-0.1.3.dist-info/WHEEL
assert_files-0.1.3.dist-info/top_level.txt
assert_files-0.1.3.dist-info/RECORD
