Metadata-Version: 2.1
Name: assert-files
Version: 0.1.3
Summary: Assert files in test automation
Home-page: https://github.com/avillanova/assert-files
Author: avillanova
License: MIT
Keywords: assert files test automation compare
Classifier: Development Status :: 1 - Planning
Classifier: Intended Audience :: Developers
Classifier: Topic :: Software Development :: Quality Assurance
Classifier: License :: OSI Approved :: MIT License
Classifier: Programming Language :: Python :: 3.9
Classifier: Programming Language :: Python :: 3.10
Requires-Python: >=3
License-File: LICENSE.txt
Requires-Dist: pypdf ~=3.16.4
